{"mean":{"confidence_interval":{"confidence_level":0.95,"lower_bound":3324596.3292968753,"upper_bound":3325699.96690625},"point_estimate":3325139.053125,"standard_error":281.1457581838912},"median":{"confidence_interval":{"confidence_level":0.95,"lower_bound":3324119.1875,"upper_bound":3325631.75},"point_estimate":3324881.71875,"standard_error":371.7419289178297},"median_abs_dev":{"confidence_interval":{"confidence_level":0.95,"lower_bound":2024.8609140515327,"upper_bound":3271.126343957148},"point_estimate":2576.2491105124354,"standard_error":314.2174411722909},"slope":null,"std_dev":{"confidence_interval":{"confidence_level":0.95,"lower_bound":2359.944563969022,"upper_bound":3274.121116483497},"point_estimate":2825.922866061942,"standard_error":234.35311933766775}}